mft2df/README.MD
mft2df/__init__.py
mft2df/mft.exe
mft2df/mft_dump.exe
mft2df/requirements.txt
mft2df/thirdparty.json
mft2df-0.13.dist-info/LICENSE.rst
mft2df-0.13.dist-info/METADATA
mft2df-0.13.dist-info/WHEEL
mft2df-0.13.dist-info/top_level.txt
mft2df-0.13.dist-info/RECORD
