Metadata-Version: 2.1
Name: mft2df
Version: 0.13
Summary: Lists the files on a drive insanely fast (43 seconds for 1,800,000 files - 600 GB) by converting the $MFT to a pandas DataFrame
Home-page: https://github.com/hansalemaos/mft2df
Author: Johannes Fischer
Author-email: aulasparticularesdealemaosp@gmail.com
License: MIT
Keywords: mft,windows,pandas
Classifier: Development Status :: 4 - Beta
Classifier: Programming Language :: Python :: 3 :: Only
Classifier: Programming Language :: Python :: 3.10
Classifier: Topic :: Software Development :: Libraries :: Python Modules
Classifier: Topic :: Utilities
License-File: LICENSE.rst
Requires-Dist: getfilenuitkapython
Requires-Dist: pandas
